ocrd/__init__.py
ocrd/constants.py
ocrd/mets_server.py
ocrd/ocrd-all-tool.json
ocrd/resolver.py
ocrd/resource_manager.py
ocrd/task_sequence.py
ocrd/workspace.py
ocrd/workspace_backup.py
ocrd/workspace_bagger.py
ocrd/cli/__init__.py
ocrd/cli/bashlib.py
ocrd/cli/network.py
ocrd/cli/ocrd_tool.py
ocrd/cli/process.py
ocrd/cli/resmgr.py
ocrd/cli/validate.py
ocrd/cli/workspace.py
ocrd/cli/zip.py
ocrd/decorators/__init__.py
ocrd/decorators/loglevel_option.py
ocrd/decorators/mets_find_options.py
ocrd/decorators/ocrd_cli_options.py
ocrd/decorators/parameter_option.py
ocrd/processor/__init__.py
ocrd/processor/base.py
ocrd/processor/helpers.py
ocrd/processor/ocrd_page_result.py
ocrd/processor/builtin/__init__.py
ocrd/processor/builtin/dummy_processor.py
ocrd/processor/builtin/filter_processor.py
ocrd/processor/builtin/merge_processor.py
ocrd/processor/builtin/param_command_header2unordered.json
ocrd/processor/builtin/param_command_heading2unordered.json
ocrd/processor/builtin/param_command_lines2orientation.json
ocrd/processor/builtin/param_command_page-update-version.json
ocrd/processor/builtin/param_command_transkribus-to-prima.json
ocrd/processor/builtin/shell_processor.py
ocrd/processor/builtin/dummy/__init__.py
ocrd/processor/builtin/dummy/ocrd-tool.json
ocrd-3.11.0.dist-info/licenses/LICENSE
ocrd_modelfactory/__init__.py
ocrd_models/__init__.py
ocrd_models/constants.py
ocrd_models/mets-empty.xml
ocrd_models/ocrd_agent.py
ocrd_models/ocrd_exif.py
ocrd_models/ocrd_file.py
ocrd_models/ocrd_mets.py
ocrd_models/ocrd_page.py
ocrd_models/ocrd_page_generateds.py
ocrd_models/ocrd_xml_base.py
ocrd_models/report.py
ocrd_models/utils.py
ocrd_models/xpath_functions.py
ocrd_network/__init__.py
ocrd_network/client.py
ocrd_network/client_utils.py
ocrd_network/constants.py
ocrd_network/database.py
ocrd_network/logging_utils.py
ocrd_network/param_validators.py
ocrd_network/process_helpers.py
ocrd_network/processing_server.py
ocrd_network/processing_worker.py
ocrd_network/resource_manager_server.py
ocrd_network/server_cache.py
ocrd-3.11.0.dist-info/METADATA
ocrd-3.11.0.dist-info/WHEEL
ocrd-3.11.0.dist-info/entry_points.txt
ocrd-3.11.0.dist-info/top_level.txt
ocrd-3.11.0.dist-info/RECORD
