Metadata-Version: 2.4
Name: ocrd
Version: 3.11.0
Summary: OCR-D framework
Author-email: Konstantin Baierer <unixprog@gmail.com>
License: Apache License 2.0
Project-URL: Homepage, https://ocr-d.de
Project-URL: Documentation, https://ocr-d.de/core
Project-URL: Repository, https://github.com/OCR-D/core
Project-URL: Issues, https://github.com/OCR-D/core/issues
Requires-Python: >=3.8
License-File: LICENSE
Requires-Dist: atomicwrites>=1.3.0
Requires-Dist: beanie>=2.0.1
Requires-Dist: click>=7
Requires-Dist: cryptography<43.0.0
Requires-Dist: cysignals
Requires-Dist: Deprecated==1.2.0
Requires-Dist: docker>=7.1.0
Requires-Dist: elementpath
Requires-Dist: fastapi>=0.78.0
Requires-Dist: filetype
Requires-Dist: Flask
Requires-Dist: frozendict>=2.4.0
Requires-Dist: gitpython
Requires-Dist: gdown
Requires-Dist: httpx>=0.22.0
Requires-Dist: importlib_metadata; python_version < "3.8"
Requires-Dist: importlib_resources; python_version < "3.10"
Requires-Dist: jsonschema>=4
Requires-Dist: pebble
Requires-Dist: lxml
Requires-Dist: memory-profiler>=0.58.0
Requires-Dist: numpy
Requires-Dist: ocrd-fork-bagit>=1.8.1.post2
Requires-Dist: ocrd-fork-bagit_profile>=1.3.0.post1
Requires-Dist: opencv-python-headless
Requires-Dist: paramiko
Requires-Dist: pika>=1.2.0
Requires-Dist: Pillow>=7.2.0
Requires-Dist: pydantic>=2.0.0
Requires-Dist: pymongo>=4.15.5
Requires-Dist: python-magic
Requires-Dist: python-multipart
Requires-Dist: pyyaml
Requires-Dist: requests
Requires-Dist: requests_unixsocket2
Requires-Dist: shapely<2.0.2; python_version < "3.9"
Requires-Dist: shapely>=2; python_version >= "3.9"
Requires-Dist: uvicorn
Requires-Dist: uvicorn>=0.17.6
Dynamic: license-file
